mycalc/caculator.py
mycalc/calculator.py
Nam_Hyeun_Sik-0.0.1.dist-info/METADATA
Nam_Hyeun_Sik-0.0.1.dist-info/WHEEL
Nam_Hyeun_Sik-0.0.1.dist-info/top_level.txt
Nam_Hyeun_Sik-0.0.1.dist-info/RECORD
