Metadata-Version: 2.1
Name: Nam-Hyeun-Sik
Version: 0.0.1
Summary: my caculator
Download-URL: https://github.com/sick2024471/calc001
Author: H S Nam
License: UNKNOWN
Platform: UNKNOWN
Classifier: Programming Language :: Python :: 3 
